{
    "Results": {
        "c": 80,
        "delivery_nodes": [
            100.0,
            100.0,
            100.0,
            100.0,
            100.0,
            100.0,
            100.0,
            100.0,
            100.0,
            100.0,
            100.0,
            100.0,
            100.0,
            100.0,
            100.0,
            100.0,
            100.0,
            100.0,
            100.0,
            100.0,
            100.0,
            100.0,
            100.0,
            100.0,
            100.0,
            100.0,
            100.0,
            100.0,
            100.0,
            100.0,
            100.0,
            100.0,
            100.0,
            100.0,
            100.0,
            100.0,
            100.0,
            100.0,
            100.0,
            100.0,
            100.0,
            100.0,
            100.0,
            100.0,
            100.0,
            100.0,
            100.0,
            100.0,
            100.0,
            100.0
        ],
        "delivery_time": [
            15.575,
            15.275,
            15.5375,
            15.3625,
            15.6875,
            15.725,
            15.6,
            15.6375,
            15.4375,
            15.675,
            14.925,
            14.8875,
            15.35,
            15.3375,
            15.2,
            16.15,
            15.6125,
            15.575,
            15.6625,
            15.525,
            16.0,
            15.5375,
            15.7375,
            15.9375,
            15.375,
            15.5125,
            15.3875,
            15.7625,
            15.4875,
            15.35,
            16.0375,
            15.5375,
            15.4875,
            15.15,
            15.3125,
            14.9625,
            14.95,
            16.0375,
            15.4,
            15.2375,
            15.0,
            15.5625,
            15.575,
            15.5375,
            15.525,
            15.9875,
            15.275,
            15.0875,
            15.5375,
            15.0125
        ],
        "disagreement": [
            0.0,
            0.0,
            0.0,
            0.0,
            0.0,
            0.0,
            0.0,
            0.0,
            0.0,
            0.0,
            0.0,
            0.0,
            0.0,
            0.0,
            0.0,
            0.0,
            0.0,
            0.0,
            0.0,
            0.0,
            0.0,
            0.0,
            0.0,
            0.0,
            0.0,
            0.0,
            0.0,
            0.0,
            0.0,
            0.0,
            0.0,
            0.0,
            0.0,
            0.0,
            0.0,
            0.0,
            0.0,
            0.0,
            0.0,
            0.0,
            0.0,
            0.0,
            0.0,
            0.0,
            0.0,
            0.0,
            0.0,
            0.0,
            0.0,
            0.0
        ],
        "disagreement_frequency": [],
        "f": 20,
        "finishing_steps": [
            3,
            3,
            3,
            3,
            3,
            3,
            3,
            3,
            3,
            3,
            3,
            3,
            3,
            3,
            3,
            3,
            3,
            3,
            3,
            3,
            3,
            3,
            3,
            3,
            3,
            3,
            3,
            3,
            3,
            3,
            3,
            3,
            3,
            3,
            3,
            3,
            3,
            3,
            3,
            3,
            3,
            3,
            3,
            3,
            3,
            3,
            3,
            3,
            3,
            3
        ],
        "n": 100,
        "p": 100,
        "termination_rate": [
            1.0,
            1.0,
            1.0,
            1.0,
            1.0,
            1.0,
            1.0,
            1.0,
            1.0,
            1.0,
            1.0,
            1.0,
            1.0,
            1.0,
            1.0,
            1.0,
            1.0,
            1.0,
            1.0,
            1.0,
            1.0,
            1.0,
            1.0,
            1.0,
            1.0,
            1.0,
            1.0,
            1.0,
            1.0,
            1.0,
            1.0,
            1.0,
            1.0,
            1.0,
            1.0,
            1.0,
            1.0,
            1.0,
            1.0,
            1.0,
            1.0,
            1.0,
            1.0,
            1.0,
            1.0,
            1.0,
            1.0,
            1.0,
            1.0,
            1.0
        ],
        "total_msgs_sent": [
            16000,
            16000,
            16000,
            16000,
            16000,
            16000,
            16000,
            16000,
            16000,
            16000,
            16000,
            16000,
            16000,
            16000,
            16000,
            16000,
            16000,
            16000,
            16000,
            16000,
            16000,
            16000,
            16000,
            16000,
            16000,
            16000,
            16000,
            16000,
            16000,
            16000,
            16000,
            16000,
            16000,
            16000,
            16000,
            16000,
            16000,
            16000,
            16000,
            16000,
            16000,
            16000,
            16000,
            16000,
            16000,
            16000,
            16000,
            16000,
            16000,
            16000
        ]
    },
    "RunTime": 129.464514352
}
