{
    "Results": {
        "c": 80,
        "delivery_nodes": [
            100.0,
            100.0,
            100.0,
            100.0,
            100.0,
            100.0,
            100.0,
            100.0,
            100.0,
            100.0,
            100.0,
            100.0,
            100.0,
            100.0,
            100.0,
            100.0,
            100.0,
            100.0,
            100.0,
            100.0,
            100.0,
            100.0,
            100.0,
            100.0,
            100.0,
            100.0,
            100.0,
            100.0,
            100.0,
            100.0,
            100.0,
            100.0,
            100.0,
            100.0,
            100.0,
            100.0,
            100.0,
            100.0,
            100.0,
            100.0,
            100.0,
            100.0,
            100.0,
            100.0,
            100.0,
            100.0,
            100.0,
            100.0,
            100.0,
            100.0
        ],
        "delivery_time": [
            15.2125,
            15.3375,
            15.5875,
            15.175,
            15.0125,
            15.3,
            14.8625,
            15.4625,
            15.5125,
            15.4375,
            15.075,
            15.2625,
            14.9,
            15.225,
            15.475,
            15.9625,
            13.925,
            15.3,
            15.0625,
            14.5125,
            15.4125,
            15.825,
            14.5625,
            15.5875,
            14.9875,
            15.3125,
            15.4125,
            15.2125,
            16.1375,
            15.8125,
            15.4625,
            15.425,
            14.7,
            15.15,
            15.65,
            14.525,
            14.625,
            14.75,
            15.05,
            15.8875,
            14.9,
            15.275,
            15.075,
            14.7125,
            14.9375,
            15.5875,
            14.5625,
            15.8125,
            14.8125,
            14.45
        ],
        "disagreement": [
            0.0,
            0.0,
            0.0,
            0.0,
            0.0,
            0.0,
            0.0,
            0.0,
            0.0,
            0.0,
            0.0,
            0.0,
            0.0,
            0.0,
            0.0,
            0.0,
            0.0,
            0.0,
            0.0,
            0.0,
            0.0,
            0.0,
            0.0,
            0.0,
            0.0,
            0.0,
            0.0,
            0.0,
            0.0,
            0.0,
            0.0,
            0.0,
            0.0,
            0.0,
            0.0,
            0.0,
            0.0,
            0.0,
            0.0,
            0.0,
            0.0,
            0.0,
            0.0,
            0.0,
            0.0,
            0.0,
            0.0,
            0.0,
            0.0,
            0.0
        ],
        "disagreement_frequency": [],
        "f": 20,
        "finishing_steps": [
            2,
            2,
            2,
            2,
            2,
            2,
            2,
            2,
            2,
            2,
            2,
            2,
            2,
            2,
            2,
            2,
            2,
            2,
            2,
            2,
            2,
            2,
            2,
            2,
            2,
            2,
            2,
            2,
            2,
            2,
            2,
            2,
            2,
            2,
            2,
            2,
            2,
            2,
            2,
            2,
            2,
            2,
            2,
            2,
            2,
            2,
            2,
            2,
            2,
            2
        ],
        "n": 100,
        "p": 90,
        "termination_rate": [
            1.0,
            1.0,
            1.0,
            1.0,
            1.0,
            1.0,
            1.0,
            1.0,
            1.0,
            1.0,
            1.0,
            1.0,
            1.0,
            1.0,
            1.0,
            1.0,
            1.0,
            1.0,
            1.0,
            1.0,
            1.0,
            1.0,
            1.0,
            1.0,
            1.0,
            1.0,
            1.0,
            1.0,
            1.0,
            1.0,
            1.0,
            1.0,
            1.0,
            1.0,
            1.0,
            1.0,
            1.0,
            1.0,
            1.0,
            1.0,
            1.0,
            1.0,
            1.0,
            1.0,
            1.0,
            1.0,
            1.0,
            1.0,
            1.0,
            1.0
        ],
        "total_msgs_sent": [
            32000,
            32000,
            32000,
            32000,
            32000,
            32000,
            32000,
            32000,
            32000,
            32000,
            32000,
            32000,
            32000,
            32000,
            32000,
            32000,
            32000,
            32000,
            32000,
            32000,
            32000,
            32000,
            32000,
            32000,
            32000,
            32000,
            32000,
            32000,
            32000,
            32000,
            32000,
            32000,
            32000,
            32000,
            32000,
            32000,
            32000,
            32000,
            32000,
            32000,
            32000,
            32000,
            32000,
            32000,
            32000,
            32000,
            32000,
            32000,
            32000,
            32000
        ]
    },
    "RunTime": 234.023656322
}
